Workbook
Name aporte: Simulador!$D$11
Name patrimonio: Simulador!$D$14
Name qtd_anos: Simulador!$D$12
Name rendimento_carteira: Simulador!$D$7
Name salario: Simulador!$D$6
Name sugestao_investimento: Simulador!$D$8
Name taxa_mensal: Simulador!$D$13

Sheet Simulador
B2: SIMULADOR DE INVESTIMENTOS EM FUNDOS IMOBILIÁRIOS (FII)
B3: Ferramenta de apoio à decisão: patrimônio acumulado, dividendos mensais e alocação por perfil
B5: CONFIGURAÇÕES DO INVESTIDOR
B6: Salário | D6: 1000
B7: Rendimento médio da carteira (dividendos) | D7: 0.006
B8: Sugestão de investimento (30% do salário) | D8: =D6*30%
B10: PARÂMETROS DA SIMULAÇÃO
B11: Quanto investir por mês? | D11: 200
B12: Por quantos anos? | D12: 5
B13: Taxa de rendimento mensal (valorização)? | D13: 0.01079
B14: Patrimônio acumulado | D14: =FV(taxa_mensal,qtd_anos*12,aporte*-1)
B15: Dividendos mensais estimados | D15: =patrimonio*rendimento_carteira
B16: Total efetivamente investido | D16: =aporte*qtd_anos*12
B17: Rendimento (juros) acumulado | D17: =patrimonio-D16
B19: CENÁRIOS - EVOLUÇÃO DO PATRIMÔNIO
A20: Ano | B20: Descrição | C20: Patrimônio | D20: Dividendo Mensal
A21: 2 | B21: Quanto em 2 anos? | C21: =FV($D$13,A21*12,$D$11*-1) | D21: =C21*rendimento_carteira
A22: 5 | B22: Quanto em 5 anos? | C22: =FV($D$13,A22*12,$D$11*-1) | D22: =C22*rendimento_carteira
A23: 10 | B23: Quanto em 10 anos? | C23: =FV($D$13,A23*12,$D$11*-1) | D23: =C23*rendimento_carteira
A24: 20 | B24: Quanto em 20 anos? | C24: =FV($D$13,A24*12,$D$11*-1) | D24: =C24*rendimento_carteira
A25: 30 | B25: Quanto em 30 anos? | C25: =FV($D$13,A25*12,$D$11*-1) | D25: =C25*rendimento_carteira
B26: PROJEÇÃO MENSAL (para visualização gráfica)
B27: Mês | C27: Patrimônio (R$) | D27: Total Investido (R$) | E27: Rendimento (R$)
B28: 1 | C28: =FV($D$13,B28,$D$11*-1) | D28: =aporte*B28 | E28: =C28-D28
B29: 2 | C29: =FV($D$13,B29,$D$11*-1) | D29: =aporte*B29 | E29: =C29-D29
B30: 3 | C30: =FV($D$13,B30,$D$11*-1) | D30: =aporte*B30 | E30: =C30-D30
B31: 4 | C31: =FV($D$13,B31,$D$11*-1) | D31: =aporte*B31 | E31: =C31-D31
B32: 5 | C32: =FV($D$13,B32,$D$11*-1) | D32: =aporte*B32 | E32: =C32-D32
B33: 6 | C33: =FV($D$13,B33,$D$11*-1) | D33: =aporte*B33 | E33: =C33-D33
B34: 7 | C34: =FV($D$13,B34,$D$11*-1) | D34: =aporte*B34 | E34: =C34-D34
B35: 8 | C35: =FV($D$13,B35,$D$11*-1) | D35: =aporte*B35 | E35: =C35-D35
B36: 9 | C36: =FV($D$13,B36,$D$11*-1) | D36: =aporte*B36 | E36: =C36-D36
B37: 10 | C37: =FV($D$13,B37,$D$11*-1) | D37: =aporte*B37 | E37: =C37-D37
B38: 11 | C38: =FV($D$13,B38,$D$11*-1) | D38: =aporte*B38 | E38: =C38-D38
B39: 12 | C39: =FV($D$13,B39,$D$11*-1) | D39: =aporte*B39 | E39: =C39-D39
B40: 13 | C40: =FV($D$13,B40,$D$11*-1) | D40: =aporte*B40 | E40: =C40-D40 | K40: PERFIL DE ALOCAÇÃO DA CARTEIRA
B41: 14 | C41: =FV($D$13,B41,$D$11*-1) | D41: =aporte*B41 | E41: =C41-D41 | K41: Perfil de risco | L41: Agressivo
B42: 15 | C42: =FV($D$13,B42,$D$11*-1) | D42: =aporte*B42 | E42: =C42-D42 | K42: Valor a ser investido por mês | L42: =aporte
B43: 16 | C43: =FV($D$13,B43,$D$11*-1) | D43: =aporte*B43 | E43: =C43-D43
B44: 17 | C44: =FV($D$13,B44,$D$11*-1) | D44: =aporte*B44 | E44: =C44-D44 | K44: Tipo de FII | L44: Percentual Sugerido | M44: Valor Mensal (R$)
B45: 18 | C45: =FV($D$13,B45,$D$11*-1) | D45: =aporte*B45 | E45: =C45-D45 | K45: PAPEL | L45: =VLOOKUP($L$41&"-"&K45,Perfis!$A:$D,4,FALSE) | M45: =L45*$L$42
B46: 19 | C46: =FV($D$13,B46,$D$11*-1) | D46: =aporte*B46 | E46: =C46-D46 | K46: TIJOLO | L46: =VLOOKUP($L$41&"-"&K46,Perfis!$A:$D,4,FALSE) | M46: =L46*$L$42
B47: 20 | C47: =FV($D$13,B47,$D$11*-1) | D47: =aporte*B47 | E47: =C47-D47 | K47: HÍBRIDOS | L47: =VLOOKUP($L$41&"-"&K47,Perfis!$A:$D,4,FALSE) | M47: =L47*$L$42
B48: 21 | C48: =FV($D$13,B48,$D$11*-1) | D48: =aporte*B48 | E48: =C48-D48 | K48: FOFs | L48: =VLOOKUP($L$41&"-"&K48,Perfis!$A:$D,4,FALSE) | M48: =L48*$L$42
B49: 22 | C49: =FV($D$13,B49,$D$11*-1) | D49: =aporte*B49 | E49: =C49-D49 | K49: DESENVOLVIMENTO | L49: =VLOOKUP($L$41&"-"&K49,Perfis!$A:$D,4,FALSE) | M49: =L49*$L$42
B50: 23 | C50: =FV($D$13,B50,$D$11*-1) | D50: =aporte*B50 | E50: =C50-D50 | K50: HOTELARIAS | L50: =VLOOKUP($L$41&"-"&K50,Perfis!$A:$D,4,FALSE) | M50: =L50*$L$42
B51: 24 | C51: =FV($D$13,B51,$D$11*-1) | D51: =aporte*B51 | E51: =C51-D51
B52: 25 | C52: =FV($D$13,B52,$D$11*-1) | D52: =aporte*B52 | E52: =C52-D52 | K52: Dica: altere os valores em azul para simular cenários e use o menu suspenso em 'Perfil de risco' (L41) para recalcular a alocação por tipo de FII.
B53: 26 | C53: =FV($D$13,B53,$D$11*-1) | D53: =aporte*B53 | E53: =C53-D53
B54: 27 | C54: =FV($D$13,B54,$D$11*-1) | D54: =aporte*B54 | E54: =C54-D54
B55: 28 | C55: =FV($D$13,B55,$D$11*-1) | D55: =aporte*B55 | E55: =C55-D55
B56: 29 | C56: =FV($D$13,B56,$D$11*-1) | D56: =aporte*B56 | E56: =C56-D56
B57: 30 | C57: =FV($D$13,B57,$D$11*-1) | D57: =aporte*B57 | E57: =C57-D57
B58: 31 | C58: =FV($D$13,B58,$D$11*-1) | D58: =aporte*B58 | E58: =C58-D58
B59: 32 | C59: =FV($D$13,B59,$D$11*-1) | D59: =aporte*B59 | E59: =C59-D59
B60: 33 | C60: =FV($D$13,B60,$D$11*-1) | D60: =aporte*B60 | E60: =C60-D60
B61: 34 | C61: =FV($D$13,B61,$D$11*-1) | D61: =aporte*B61 | E61: =C61-D61
B62: 35 | C62: =FV($D$13,B62,$D$11*-1) | D62: =aporte*B62 | E62: =C62-D62
B63: 36 | C63: =FV($D$13,B63,$D$11*-1) | D63: =aporte*B63 | E63: =C63-D63
B64: 37 | C64: =FV($D$13,B64,$D$11*-1) | D64: =aporte*B64 | E64: =C64-D64
... B87: 60 | C87: =FV($D$13,B87,$D$11*-1) | D87: =aporte*B87 | E87: =C87-D87

Sheet Perfis
A1: TABELA DE PERFIS E ALOCAÇÃO POR TIPO DE FII
A2: CHAVE | B2: PERFIL | C2: TIPO DE FII | D2: %
A3: =B3&"-"&C3 | B3: Conservador | C3: PAPEL | D3: 0.3
A4: =B4&"-"&C4 | B4: Conservador | C4: TIJOLO | D4: 0.5
A5: =B5&"-"&C5 | B5: Conservador | C5: HÍBRIDOS | D5: 0.1
A6: =B6&"-"&C6 | B6: Conservador | C6: FOFs | D6: 0.1
A7: =B7&"-"&C7 | B7: Conservador | C7: DESENVOLVIMENTO | D7: 0
A8: =B8&"-"&C8 | B8: Conservador | C8: HOTELARIAS | D8: 0
A9: =B9&"-"&C9 | B9: Moderado | C9: PAPEL | D9: 0.32
A10: =B10&"-"&C10 | B10: Moderado | C10: TIJOLO | D10: 0.35
A11: =B11&"-"&C11 | B11: Moderado | C11: HÍBRIDOS | D11: 0.08
A12: =B12&"-"&C12 | B12: Moderado | C12: FOFs | D12: 0.05
A13: =B13&"-"&C13 | B13: Moderado | C13: DESENVOLVIMENTO | D13: 0.1
A14: =B14&"-"&C14 | B14: Moderado | C14: HOTELARIAS | D14: 0.1
... A20: =B20&"-"&C20 | B20: Agressivo | C20: HOTELARIAS | D20: 0.1
A22: Os percentuais representam a sugestão de alocação do aporte mensal conforme o perfil de risco selecionado.
